src/__init__.py
src/logger.py
src/main.py
src/version.py
src/analytics/__init__.py
src/analytics/manager.py
src/api/common.py
src/api/types.py
src/api/prompts/__init__.py
src/api/prompts/prompts.py
src/api/prompts/register.py
src/api/prompts/types.py
src/api/resources/__init__.py
src/api/resources/register.py
src/api/resources/resources.py
src/api/resources/types.py
src/api/resources/docs/singlestore-drizzle.mdc
src/api/tools/__init__.py
src/api/tools/registery.py
src/api/tools/s2_manager.py
src/api/tools/tools.py
src/api/tools/types.py
src/api/tools/database/__init__.py
src/api/tools/database/database.py
src/api/tools/jobs/__init__.py
src/api/tools/jobs/jobs.py
src/api/tools/jobs/utils.py
src/api/tools/notebooks/__init__.py
src/api/tools/notebooks/notebook-schema.json
src/api/tools/notebooks/notebooks.py
src/api/tools/notebooks/types.py
src/api/tools/notebooks/utils.py
src/api/tools/organization/__init__.py
src/api/tools/organization/organization.py
src/api/tools/organization/utils.py
src/api/tools/regions/__init__.py
src/api/tools/regions/regions.py
src/api/tools/regions/utils.py
src/api/tools/starter_workspaces/__init__.py
src/api/tools/starter_workspaces/starter_workspaces.py
src/api/tools/user/__init__.py
src/api/tools/user/user.py
src/api/tools/workspaces/__init__.py
src/api/tools/workspaces/utils.py
src/api/tools/workspaces/workspace_groups.py
src/api/tools/workspaces/workspaces.py
src/auth/__init__.py
src/auth/browser_auth.py
src/auth/callback.py
src/auth/oauth_schema.sql
src/auth/provider.py
src/auth/session_credentials_manager.py
src/auth/success_page.html
src/auth/models/__init__.py
src/auth/models/models.py
src/commands/__init__.py
src/commands/constants.py
src/commands/init.py
src/commands/start.py
src/config/__init__.py
src/config/config.py
src/utils/__init__.py
src/utils/elicitation.py
src/utils/uuid_validation.py
singlestore_mcp_server_fastmcp-0.4.12.dist-info/METADATA
singlestore_mcp_server_fastmcp-0.4.12.dist-info/WHEEL
singlestore_mcp_server_fastmcp-0.4.12.dist-info/entry_points.txt
singlestore_mcp_server_fastmcp-0.4.12.dist-info/licenses/LICENSE
singlestore_mcp_server_fastmcp-0.4.12.dist-info/RECORD
