Metadata-Version: 2.4
Name: singlestore_mcp_server-fastmcp
Version: 0.4.12
Summary: SingleStore MCP server
Project-URL: Homepage, https://github.com/fastmcp-me/mcp-server-singlestore#readme
Project-URL: Repository, https://github.com/fastmcp-me/mcp-server-singlestore.git
Project-URL: Issues, https://github.com/fastmcp-me/mcp-server-singlestore/issues
License-File: LICENSE
Requires-Python: >=3.10
Requires-Dist: jsonschema>=4.0.0
Requires-Dist: mcp>=1.10.1
Requires-Dist: nbformat>=5.10.4
Requires-Dist: pre-commit>=4.2.0
Requires-Dist: pydantic-settings>=2.9.1
Requires-Dist: pytest-asyncio>=1.1.0
Requires-Dist: segment-analytics-python>=2.3.4
Requires-Dist: singlestoredb>=1.15.1
Requires-Dist: starlette>=0.46.2
